[
  {
    "name": "Centres",
    "sector": "",
    "drInCharge": "",
    "address": "",
    "addressWithUnit": "",
    "tel": "",
    "email": ""
  },
  {
    "name": "Alor Setar",
    "sector": "",
    "drInCharge": "",
    "address": "",
    "addressWithUnit": "",
    "tel": "",
    "email": ""
  },
  {
    "name": "Sultanah Bahiyah Hospital, CAPD Unit",
    "sector": "MOH",
    "drInCharge": "CHING CHEN HUA;",
    "address": "",
    "addressWithUnit": "",
    "tel": "",
    "email": ""
  },
  {
    "name": "",
    "sector": "",
    "drInCharge": "",
    "address": "CAPD Unit\nHospital Sultanah Bahiyah\nKM 6, Jalan Langgar  05460 Alor Setar  Kedah Darul Aman  MALAYSIA",
    "addressWithUnit": "Sultanah Bahiyah Hospital, CAPD Unit",
    "tel": "( 04)7406233  7940",
    "email": "Tel (2):"
  },
  {
    "name": "Alor Setar Dialysis Centre, HD Unit",
    "sector": "PRIVATE",
    "drInCharge": "TEH SOO KIM;",
    "address": "",
    "addressWithUnit": "",
    "tel": "",
    "email": ""
  },
  {
    "name": "",
    "sector": "",
    "drInCharge": "",
    "address": "Alor Setar Dialysis Centre\nNo. 300, Jalan Tandop 3\nKawasan Perusahaan Tandop Baru  05050 Alor Setar  Kedah Darul Aman  MALAYSIA",
    "addressWithUnit": "Alor Setar Dialysis Centre, HD Unit",
    "tel": "( 04)7715193",
    "email": "Fax:"
  },
  {
    "name": "Buddhist Tzu-Chi Dialysis Centre (Kedah), HD Unit",
    "sector": "NGO",
    "drInCharge": "NG WEI SIONG;",
    "address": "",
    "addressWithUnit": "",
    "tel": "",
    "email": ""
  },
  {
    "name": "",
    "sector": "",
    "drInCharge": "",
    "address": "Buddhist Tzu-Chi Dialysis Centre (Kedah)\n(Pertubuhan Buddhist Tzu Chi Merits Malaysia)\nNo. 535A, Jalan Perak\nKawasan Perindustrian Mergong 2  05350 Alor Setar  Kedah Darul Aman  MALAYSIA",
    "addressWithUnit": "Buddhist Tzu-Chi Dialysis Centre (Kedah), HD Unit",
    "tel": "( 04)7323604  101",
    "email": "Fax:"
  },
  {
    "name": "Dialisis Dr Zur Sdn Bhd (Cawangan Alor Setar), HD Unit",
    "sector": "PRIVATE",
    "drInCharge": "SHERLINA BINTI HILMY;",
    "address": "",
    "addressWithUnit": "",
    "tel": "",
    "email": ""
  },
  {
    "name": "",
    "sector": "",
    "drInCharge": "",
    "address": "Dialisis Dr Zur Sdn Bhd (Cawangan Alor Setar)\nNo. 8, (Ground & First Floor), Susuran Mas Merah\nTaman Mas Maju, Titi Gajah  06550 Alor Setar  Kedah Darul Aman  MALAYSIA",
    "addressWithUnit": "Dialisis Dr Zur Sdn Bhd (Cawangan Alor Setar), HD Unit",
    "tel": "017-9262100",
    "email": "eNRR"
  },
  {
    "name": "Pusat Dialisis Albukhary, HD Unit",
    "sector": "PRIVATE",
    "drInCharge": "NG WEI SIONG;",
    "address": "",
    "addressWithUnit": "",
    "tel": "",
    "email": ""
  },
  {
    "name": "",
    "sector": "",
    "drInCharge": "",
    "address": "Pusat dialysis Albukhary\n(Energetic Advantage Sdn Bhd)\nKompleks Albukhary\nJalan Langgar  05460 Alor Setar  Kedah Darul Aman  MALAYSIA",
    "addressWithUnit": "Pusat Dialisis Albukhary, HD Unit",
    "tel": "( 04)7322121",
    "email": "Email:"
  },
  {
    "name": "Pusat Dialisis Davita Alor Setar, HD Unit",
    "sector": "PRIVATE",
    "drInCharge": "NAZIL NUHAIRI BIN ISMAIL;",
    "address": "",
    "addressWithUnit": "",
    "tel": "",
    "email": ""
  },
  {
    "name": "",
    "sector": "",
    "drInCharge": "",
    "address": "Pusat Dialisis Davita Alor Setar,\nNo. 17 & 18, Jalan Bistari 1, Taman Bistari\nLebuhraya Sultan Abdul Halim  05400 Alor Setar  Kedah Darul Aman  MALAYSIA",
    "addressWithUnit": "Pusat Dialisis Davita Alor Setar, HD Unit",
    "tel": "( 04)7714644",
    "email": "Fax:"
  },
  {
    "name": "Pusat Dialisis Marjina (Ayer Hitam), HD Unit",
    "sector": "PRIVATE",
    "drInCharge": "ZAKI ZAMANI BIN ABD RASHID;",
    "address": "",
    "addressWithUnit": "",
    "tel": "",
    "email": ""
  },
  {
    "name": "",
    "sector": "",
    "drInCharge": "",
    "address": "No 4 Pusat Perniagaan Arowana, Pekan Ayer Hitam, Jerlun  06150 Alor Setar  Kedah Darul Aman  MALAYSIA",
    "addressWithUnit": "Pusat Dialisis Marjina (Ayer Hitam), HD Unit",
    "tel": "( 04)7942581",
    "email": "Email:"
  },
  {
    "name": "Pusat Dialisis Marjina, HD Unit",
    "sector": "PRIVATE",
    "drInCharge": "HABIBAH BINTI ITHNIN;",
    "address": "",
    "addressWithUnit": "",
    "tel": "",
    "email": ""
  },
  {
    "name": "",
    "sector": "",
    "drInCharge": "",
    "address": "Pusat Dialisis Marjina Sdn Bhd\nNo. 3 & 4, Lot 320, Bangunan Persatuan Warga Bimbingan\nKM 6, Jalan Langgar  05460 Alor Setar  Kedah Darul Aman  MALAYSIA",
    "addressWithUnit": "Pusat Dialisis Marjina, HD Unit",
    "tel": "( 04)7877013  7042",
    "email": "Tel (2):"
  },
  {
    "name": "Pusat Dialisis NKF-Kelab Lions Alor Star, HD Unit",
    "sector": "NGO",
    "drInCharge": "",
    "address": "",
    "addressWithUnit": "",
    "tel": "",
    "email": ""
  },
  {
    "name": "",
    "sector": "",
    "drInCharge": "",
    "address": "Pusat Dialisis NKF-Kelab Lions Alor Star\n(National Kidney Foundation of Malaysia)\nNo. 96-97, Jalan Kristal 6\nTaman Perindustrian Ringan Kristal  05150 Alor Setar  Kedah Darul Aman  MALAYSIA",
    "addressWithUnit": "Pusat Dialisis NKF-Kelab Lions Alor Star, HD Unit",
    "tel": "( 04)7352190",
    "email": "Email:"
  },
  {
    "name": "Pusat Haemodialisis Dr. Ismail, HD Unit",
    "sector": "PRIVATE",
    "drInCharge": "NAZIL NUHAIRI BIN ISMAIL;",
    "address": "",
    "addressWithUnit": "",
    "tel": "",
    "email": ""
  },
  {
    "name": "",
    "sector": "",
    "drInCharge": "",
    "address": "Pusat Haemodialisis Dr. Ismail Sdn Bhd\nNo. 281-282, Taman Anggerik, Fasa 3\nJalan Lencong Barat  05050 Alor Setar  Kedah Darul Aman  MALAYSIA",
    "addressWithUnit": "Pusat Haemodialisis Dr. Ismail, HD Unit",
    "tel": "( 04)7771193",
    "email": "Fax:"
  },
  {
    "name": "Pusat Haemodialisis Zakat Kedah, HD Unit",
    "sector": "NGO",
    "drInCharge": "NAZIL NUHAIRI BIN ISMAIL;",
    "address": "",
    "addressWithUnit": "",
    "tel": "",
    "email": ""
  },
  {
    "name": "",
    "sector": "",
    "drInCharge": "",
    "address": "Pusat Haemodialisis Zakat Kedah\n(Pertubuhan Haemodialisis Zakat Kedah)\nAras Bawah, Menara Zakat\nJalan Telok Wanjah  05200 Alor Setar  Kedah Darul Aman  MALAYSIA",
    "addressWithUnit": "Pusat Haemodialisis Zakat Kedah, HD Unit",
    "tel": "( 04)7306275",
    "email": "Fax:"
  },
  {
    "name": "Pusat Hemodialisis Mergong, HD Unit",
    "sector": "PRIVATE",
    "drInCharge": "ROASHRI NOR B NORDIN;",
    "address": "",
    "addressWithUnit": "",
    "tel": "",
    "email": ""
  },
  {
    "name": "",
    "sector": "",
    "drInCharge": "",
    "address": "Pusat Hemodialisis Mergong\nNo. 67, Jalan Shahab 7\nKompleks Shahab Perdana  05150 Alor Setar  Kedah Darul Aman  MALAYSIA",
    "addressWithUnit": "Pusat Hemodialisis Mergong, HD Unit",
    "tel": "( 04)7351581",
    "email": "Email:"
  },
  {
    "name": "Pusat Rawatan Hemodialisis Tunku Sarina, HD Unit",
    "sector": "NGO",
    "drInCharge": "MOHD HAFIZ NAIM BIN MUSTAFFA;",
    "address": "",
    "addressWithUnit": "",
    "tel": "",
    "email": ""
  },
  {
    "name": "",
    "sector": "",
    "drInCharge": "",
    "address": "Pusat Rawatan Hemodialisis Tunku Sarina\nNo. 964, Rumah Kerajaan \nSungai Korok  05400 Alor Setar  Kedah Darul Aman  MALAYSIA",
    "addressWithUnit": "Pusat Rawatan Hemodialisis Tunku Sarina, HD Unit",
    "tel": "( 04)7721690",
    "email": "Email:"
  },
  {
    "name": "Putra Medical Centre, HD Unit",
    "sector": "PRIVATE",
    "drInCharge": "LIM HUI LING;",
    "address": "",
    "addressWithUnit": "",
    "tel": "",
    "email": ""
  },
  {
    "name": "",
    "sector": "",
    "drInCharge": "",
    "address": "Haemodialysis Unit\nPutra Medical Centre\nNo. 888, Jalan Sekerat, Off Jalan Putra  05100 Alor Setar  Kedah Darul Aman  MALAYSIA",
    "addressWithUnit": "Putra Medical Centre, HD Unit",
    "tel": "( 04)7342888  1303",
    "email": "Fax:"
  },
  {
    "name": "Renal Care (Kedah), HD Unit",
    "sector": "PRIVATE",
    "drInCharge": "",
    "address": "",
    "addressWithUnit": "",
    "tel": "",
    "email": ""
  },
  {
    "name": "",
    "sector": "",
    "drInCharge": "",
    "address": "Renal Care\nKedah Medical Centre\nPumpong  05250 Alor Setar  Kedah Darul Aman  MALAYSIA",
    "addressWithUnit": "Renal Care (Kedah), HD Unit",
    "tel": "( 04)7308878  8269 /8264",
    "email": "Tel (2):"
  },
  {
    "name": "Sultanah Bahiyah Hospital, HD Unit",
    "sector": "MOH",
    "drInCharge": "MOHAMMAD FAISAL BIN ASMEE;",
    "address": "",
    "addressWithUnit": "",
    "tel": "",
    "email": ""
  },
  {
    "name": "",
    "sector": "",
    "drInCharge": "",
    "address": "Haemodialysis Unit\nHospital Sultanah Bahiyah\nKM 6, Jalan Langgar  05460 Alor Setar  Kedah Darul Aman  MALAYSIA",
    "addressWithUnit": "Sultanah Bahiyah Hospital, HD Unit",
    "tel": "( 04)7746202",
    "email": "Email:"
  },
  {
    "name": "Superkids Trinity-NKF Dialysis Centre, HD Unit",
    "sector": "NGO",
    "drInCharge": "EASON CHANG;",
    "address": "",
    "addressWithUnit": "",
    "tel": "",
    "email": ""
  },
  {
    "name": "",
    "sector": "",
    "drInCharge": "",
    "address": "Superkids Trinity-NKF Dialysis Centre\nNo. 60-B, Jalan Bakar Bata  05100 Alor Setar  Kedah Darul Aman  MALAYSIA",
    "addressWithUnit": "Superkids Trinity-NKF Dialysis Centre, HD Unit",
    "tel": "( 04)7340215",
    "email": "Email:"
  },
  {
    "name": "Sultanah Bahiyah Hospital, Tx Unit",
    "sector": "MOH",
    "drInCharge": "CHING CHEN HUA;",
    "address": "",
    "addressWithUnit": "",
    "tel": "",
    "email": ""
  },
  {
    "name": "",
    "sector": "",
    "drInCharge": "",
    "address": "Renal Transplant Clinic\nc/o Haemodialysis Unit\nHospital Sultanah Bahiyah  05460 Alor Setar  Kedah Darul Aman  MALAYSIA",
    "addressWithUnit": "Sultanah Bahiyah Hospital, Tx Unit",
    "tel": "( 04)7746202",
    "email": "Email:"
  },
  {
    "name": "Sultanah Bahiyah Hospital, MRRB Unit",
    "sector": "MOH",
    "drInCharge": "CHING CHEN HUA;",
    "address": "",
    "addressWithUnit": "",
    "tel": "",
    "email": ""
  },
  {
    "name": "",
    "sector": "",
    "drInCharge": "",
    "address": "Depatment of Medicine\nHospital Sultanah Bahiyah  06550 Alor Setar  Kedah Darul Aman  MALAYSIA",
    "addressWithUnit": "Sultanah Bahiyah Hospital, MRRB Unit",
    "tel": "( 04)7406233  6739",
    "email": "Fax:"
  },
  {
    "name": "Baling",
    "sector": "",
    "drInCharge": "",
    "address": "",
    "addressWithUnit": "",
    "tel": "",
    "email": ""
  },
  {
    "name": "Baling Hospital, HD Unit",
    "sector": "MOH",
    "drInCharge": "LIM YIK SHEN;",
    "address": "",
    "addressWithUnit": "",
    "tel": "",
    "email": ""
  },
  {
    "name": "",
    "sector": "",
    "drInCharge": "",
    "address": "Haemodialysis Unit\nHospital Baling  09100 Baling  Kedah Darul Aman  MALAYSIA",
    "addressWithUnit": "Baling Hospital, HD Unit",
    "tel": "( 04)4701333  1403 /1405",
    "email": "Tel (2):"
  },
  {
    "name": "Pusat Dialisis Baling, HD Unit",
    "sector": "PRIVATE",
    "drInCharge": "TAI WENG YEW;",
    "address": "",
    "addressWithUnit": "",
    "tel": "",
    "email": ""
  },
  {
    "name": "",
    "sector": "",
    "drInCharge": "",
    "address": "Pusat Dialisis Baling\nNo. 3B, 4B & 5B, Jalan Desa Camelia 1\nTaman Desa Camelia  09100 Baling  Kedah Darul Aman  MALAYSIA",
    "addressWithUnit": "Pusat Dialisis Baling, HD Unit",
    "tel": "04-4769127",
    "email": "eNRR"
  },
  {
    "name": "Pusat Hemodialisis Seroja (Baling), HD Unit",
    "sector": "PRIVATE",
    "drInCharge": "ZARULHISHAM BIN KASSIM;",
    "address": "",
    "addressWithUnit": "",
    "tel": "",
    "email": ""
  },
  {
    "name": "",
    "sector": "",
    "drInCharge": "",
    "address": "Pusat Hemodialisis Seroja Sdn Bhd (Cawangan Baling)\nNo. 7, Persisiran Kota 1/5 \nKota Baling Jaya, Batu 42 Pulai  09100 Baling  Kedah Darul Aman  MALAYSIA",
    "addressWithUnit": "Pusat Hemodialisis Seroja (Baling), HD Unit",
    "tel": "( 04)4708028",
    "email": "Fax:"
  },
  {
    "name": "Changloon",
    "sector": "",
    "drInCharge": "",
    "address": "",
    "addressWithUnit": "",
    "tel": "",
    "email": ""
  },
  {
    "name": "Northern Dialysis Centre, HD Unit",
    "sector": "PRIVATE",
    "drInCharge": "ZAINUDDIN BIN BADARUDDIN;",
    "address": "",
    "addressWithUnit": "",
    "tel": "",
    "email": ""
  },
  {
    "name": "",
    "sector": "",
    "drInCharge": "",
    "address": "Northern Dialysis Centre Sdn Bhd\nWisma NDC, No. 26, Jalan Teja 1\nTaman Teja  06010 Changloon  Kedah Darul Aman  MALAYSIA",
    "addressWithUnit": "Northern Dialysis Centre, HD Unit",
    "tel": "( 04)9249200",
    "email": "Email:"
  },
  {
    "name": "Changlun",
    "sector": "",
    "drInCharge": "",
    "address": "",
    "addressWithUnit": "",
    "tel": "",
    "email": ""
  },
  {
    "name": "Pusat Rawatan Dialisis Al Farabi, HD Unit",
    "sector": "PRIVATE",
    "drInCharge": "AZRAF MUHAMMAD FITRI BIN AUZIZ;",
    "address": "",
    "addressWithUnit": "",
    "tel": "",
    "email": ""
  },
  {
    "name": "",
    "sector": "",
    "drInCharge": "",
    "address": "Pusat Rawatan Dialisis Al Farabi Sdn Bhd\nLot 203 & 204, Jalan Nyatoh,\nKampung Tradisi Lembah Keriang  06010 Changlun  Kedah Darul Aman  MALAYSIA",
    "addressWithUnit": "Pusat Rawatan Dialisis Al Farabi, HD Unit",
    "tel": "04-9243862",
    "email": "Email:"
  },
  {
    "name": "Guar Chempedak",
    "sector": "",
    "drInCharge": "",
    "address": "",
    "addressWithUnit": "",
    "tel": "",
    "email": ""
  },
  {
    "name": "Pusat Haemodialisis Dr Ismail (Cawangan Guar Chempedak), HD Unit",
    "sector": "PRIVATE",
    "drInCharge": "HABIBAH BINTI ITHNIN;",
    "address": "",
    "addressWithUnit": "",
    "tel": "",
    "email": ""
  },
  {
    "name": "",
    "sector": "",
    "drInCharge": "",
    "address": "Pusat Haemodialisis Dr Ismail Sdn Bhd (Cawangan Guar Chempedak)\nNo 58, Jalan Chempedak Indah 1\nTaman Chempedak Indah  08800 Guar Chempedak  Kedah Darul Aman  MALAYSIA",
    "addressWithUnit": "Pusat Haemodialisis Dr Ismail (Cawangan Guar Chempedak), HD Unit",
    "tel": "( 04)4688336",
    "email": "Email:"
  },
  {
    "name": "Gurun",
    "sector": "",
    "drInCharge": "",
    "address": "",
    "addressWithUnit": "",
    "tel": "",
    "email": ""
  },
  {
    "name": "Pusat Dialisis Davita Gurun",
    "sector": "PRIVATE",
    "drInCharge": "CHEW SHI WEI;",
    "address": "",
    "addressWithUnit": "",
    "tel": "",
    "email": ""
  },
  {
    "name": "",
    "sector": "",
    "drInCharge": "",
    "address": "Pusat Dialisis Davita Gurun\n(Quality Dialysis Care Sdn Bhd)\nNo. 48 & 49, Ground Floor\nPekan Gurun  08300 Gurun  Kedah Darul Aman  MALAYSIA",
    "addressWithUnit": "Pusat Dialisis Davita Gurun",
    "tel": "(016)2267686",
    "email": "eNRR"
  },
  {
    "name": "Pusat Dialisis Mukmin Gurun, HD Unit",
    "sector": "PRIVATE",
    "drInCharge": "MUAZZATUN NOOR BT MURAD;",
    "address": "",
    "addressWithUnit": "",
    "tel": "",
    "email": ""
  },
  {
    "name": "",
    "sector": "",
    "drInCharge": "",
    "address": "Pusat Dialisis Mukmin Gurun\nNo. 1,2,3, Kedai Dua Tingkat, Taman Sri Utama Indah\nJalan Sungai Petani  08300 Gurun  Kedah Darul Aman  MALAYSIA",
    "addressWithUnit": "Pusat Dialisis Mukmin Gurun, HD Unit",
    "tel": "( 04)4684027",
    "email": "Fax:"
  },
  {
    "name": "Jitra",
    "sector": "",
    "drInCharge": "",
    "address": "",
    "addressWithUnit": "",
    "tel": "",
    "email": ""
  },
  {
    "name": "Jitra Hospital, HD Unit",
    "sector": "MOH",
    "drInCharge": "CHING CHEN HUA;",
    "address": "",
    "addressWithUnit": "",
    "tel": "",
    "email": ""
  },
  {
    "name": "",
    "sector": "",
    "drInCharge": "",
    "address": "Unit Haemodialysis\nJitra Hospital\nJalan Changlun  06000 Jitra  Kedah Darul Aman  MALAYSIA",
    "addressWithUnit": "Jitra Hospital, HD Unit",
    "tel": "04-9174333  107 / 163",
    "email": "Tel (2):"
  },
  {
    "name": "Pusat Dialisis Al-Hayat, HD Unit",
    "sector": "PRIVATE",
    "drInCharge": "ZAKI ZAMANI BIN ABD RASHID;",
    "address": "",
    "addressWithUnit": "",
    "tel": "",
    "email": ""
  },
  {
    "name": "",
    "sector": "",
    "drInCharge": "",
    "address": "Pusat Dialisis Al-Hayat\n(ADM Diaysis Centre Sdn Bhd)\nNo. 4A/4B, KM25, Telok Keluang\nMukim Tunjang  06000 Jitra  Kedah Darul Aman  MALAYSIA",
    "addressWithUnit": "Pusat Dialisis Al-Hayat, HD Unit",
    "tel": "0124961914",
    "email": "Email:"
  },
  {
    "name": "Pusat Hemodialisis Dr Azhar (Jitra), HD Unit",
    "sector": "PRIVATE",
    "drInCharge": "AZRAF MUHAMMAD FITRI BIN AUZIZ;",
    "address": "",
    "addressWithUnit": "",
    "tel": "",
    "email": ""
  },
  {
    "name": "",
    "sector": "",
    "drInCharge": "",
    "address": "Pusat Hemodialisis Dr Azhar\nLot 227, Lorong 2-2, Kompleks Jitra 2  06000 Jitra  Kedah Darul Aman  MALAYSIA",
    "addressWithUnit": "Pusat Hemodialisis Dr Azhar (Jitra), HD Unit",
    "tel": "( 04)9131826",
    "email": "eNRR"
  },
  {
    "name": "Zaharah Dialisis Center (Jitra), HD Unit",
    "sector": "PRIVATE",
    "drInCharge": "AHMAD FAKARUDDIN B AHMAD SAMSUDDIN;",
    "address": "",
    "addressWithUnit": "",
    "tel": "",
    "email": ""
  },
  {
    "name": "",
    "sector": "",
    "drInCharge": "",
    "address": "Zaharah Dialisis Center Sdn Bhd\nNo. 122 & 123, Taman Tengku Maheran 5\nBandar Darul Aman  06000 Jitra  Kedah Darul Aman  MALAYSIA",
    "addressWithUnit": "Zaharah Dialisis Center (Jitra), HD Unit",
    "tel": "( 04)9179848",
    "email": "Fax:"
  },
  {
    "name": "Kodiang",
    "sector": "",
    "drInCharge": "",
    "address": "",
    "addressWithUnit": "",
    "tel": "",
    "email": ""
  },
  {
    "name": "Pusat Dialisis Remedic Kodiang, HD Unit",
    "sector": "PRIVATE",
    "drInCharge": "LIM HUI LING;",
    "address": "",
    "addressWithUnit": "",
    "tel": "",
    "email": ""
  },
  {
    "name": "",
    "sector": "",
    "drInCharge": "",
    "address": "Pusat Dialisis Remedic Kodiang\nNo. 50 (Tingkat Atas Dan Tingkat Bawah)\nJalan Bahagia 3/1, Taman Bahagia  06100 Kodiang  Kedah Darul Aman  MALAYSIA",
    "addressWithUnit": "Pusat Dialisis Remedic Kodiang, HD Unit",
    "tel": "Datin Dr. LIM HUI LING",
    "email": "Doctor in charge"
  },
  {
    "name": "Unit Hemodialisis Komuntiti Kodiang, HD Unit",
    "sector": "MOH",
    "drInCharge": "CHING CHEN HUA;",
    "address": "",
    "addressWithUnit": "",
    "tel": "",
    "email": ""
  },
  {
    "name": "",
    "sector": "",
    "drInCharge": "",
    "address": "Unit Hemodialisis Komuntiti Kodiang\nPusat Kesihatan Kodiang  06100 Kodiang  Kedah Darul Aman  MALAYSIA",
    "addressWithUnit": "Unit Hemodialisis Komuntiti Kodiang, HD Unit",
    "tel": "( 04)9250103",
    "email": "eNRR"
  },
  {
    "name": "Kota Sarang Semut",
    "sector": "",
    "drInCharge": "",
    "address": "",
    "addressWithUnit": "",
    "tel": "",
    "email": ""
  },
  {
    "name": "Pusat Hemodialisis Alfaisal, HD Unit",
    "sector": "PRIVATE",
    "drInCharge": "HABIBAH BINTI ITHNIN;",
    "address": "",
    "addressWithUnit": "",
    "tel": "",
    "email": ""
  },
  {
    "name": "",
    "sector": "",
    "drInCharge": "",
    "address": "Pusat Hemodialisis Alfaisal Sdn Bhd\n55, Kompleks Perniagaan Wawasan\nJalan Wawasan 2  06800 Kota Sarang Semut  Kedah Darul Aman  MALAYSIA",
    "addressWithUnit": "Pusat Hemodialisis Alfaisal, HD Unit",
    "tel": "04-7691277",
    "email": "Email:"
  },
  {
    "name": "Kuala Kedah",
    "sector": "",
    "drInCharge": "",
    "address": "",
    "addressWithUnit": "",
    "tel": "",
    "email": ""
  },
  {
    "name": "Pusat Dialisis Myangkasa (K. Kedah), HD Unit",
    "sector": "PRIVATE",
    "drInCharge": "ZAKI ZAMANI BIN ABD RASHID;",
    "address": "",
    "addressWithUnit": "",
    "tel": "",
    "email": ""
  },
  {
    "name": "",
    "sector": "",
    "drInCharge": "",
    "address": "Pusat Dialisis Myangkasa\nNo. 32, 33, Jalan Sri Dayung 4\nTaman Sri Dayung, Mukim Teluk Kechai  06600 Kuala Kedah  Kedah Darul Aman  MALAYSIA",
    "addressWithUnit": "Pusat Dialisis Myangkasa (K. Kedah), HD Unit",
    "tel": "(04)7622722",
    "email": "Fax:"
  },
  {
    "name": "Kuala Ketil",
    "sector": "",
    "drInCharge": "",
    "address": "",
    "addressWithUnit": "",
    "tel": "",
    "email": ""
  },
  {
    "name": "Pusat Dialisis Ibnu Sina (Kuala Ketil), HD Unit",
    "sector": "PRIVATE",
    "drInCharge": "NOORULAMIN BIN ABDUL RAHMAN;",
    "address": "",
    "addressWithUnit": "",
    "tel": "",
    "email": ""
  },
  {
    "name": "",
    "sector": "",
    "drInCharge": "",
    "address": "Pusat Dialisis Ibnu Sina (Cawangan Kuala Ketil)\n(Beyond Medicare Sdn Bhd)\nNo. 225, Lorong Puteri 8\nTaman Tanjung Puteri  09300 Kuala Ketil  Kedah Darul Aman  MALAYSIA",
    "addressWithUnit": "Pusat Dialisis Ibnu Sina (Kuala Ketil), HD Unit",
    "tel": "012-9815199",
    "email": "Fax:"
  },
  {
    "name": "Pusat Dialisis Nusa Bestari Dialysis Sdn Bhd, HD Unit",
    "sector": "PRIVATE",
    "drInCharge": "ROBERT LING KUI EE;",
    "address": "",
    "addressWithUnit": "",
    "tel": "",
    "email": ""
  },
  {
    "name": "",
    "sector": "",
    "drInCharge": "",
    "address": "Pusat Dialisis Nusa Bestari Dialysis Sdn Bhd\n6, Jalan Bestari 1\nTaman Bestari  09300 Kuala Ketil  Kedah Darul Aman  MALAYSIA",
    "addressWithUnit": "Pusat Dialisis Nusa Bestari Dialysis Sdn Bhd, HD Unit",
    "tel": "017-7049133",
    "email": "eNRR"
  },
  {
    "name": "Kuala Nerang",
    "sector": "",
    "drInCharge": "",
    "address": "",
    "addressWithUnit": "",
    "tel": "",
    "email": ""
  },
  {
    "name": "Kuala Nerang Hospital, HD Unit",
    "sector": "MOH",
    "drInCharge": "CHING CHEN HUA;",
    "address": "",
    "addressWithUnit": "",
    "tel": "",
    "email": ""
  },
  {
    "name": "",
    "sector": "",
    "drInCharge": "",
    "address": "Haemodialysis Unit\nHospital Kuala Nerang  06300 Kuala Nerang  Kedah Darul Aman  MALAYSIA",
    "addressWithUnit": "Kuala Nerang Hospital, HD Unit",
    "tel": "04-7867049  227",
    "email": "Fax:"
  },
  {
    "name": "Kulim",
    "sector": "",
    "drInCharge": "",
    "address": "",
    "addressWithUnit": "",
    "tel": "",
    "email": ""
  },
  {
    "name": "Kulim Hospital, CAPD Unit",
    "sector": "MOH",
    "drInCharge": "LIM YIK SHEN;",
    "address": "",
    "addressWithUnit": "",
    "tel": "",
    "email": ""
  },
  {
    "name": "",
    "sector": "",
    "drInCharge": "",
    "address": "CAPD Unit\nHospital Kulim\nLebuh Hi-Tech  09090 Kulim  Kedah Darul Aman  MALAYSIA",
    "addressWithUnit": "Kulim Hospital, CAPD Unit",
    "tel": "04-4272733  3567",
    "email": "Fax:"
  },
  {
    "name": "Darul Aman Ventures, HD Unit",
    "sector": "PRIVATE",
    "drInCharge": "RUSLI BIN HAMID;",
    "address": "",
    "addressWithUnit": "",
    "tel": "",
    "email": ""
  },
  {
    "name": "",
    "sector": "",
    "drInCharge": "",
    "address": "Darul Aman Ventures \nC/O Putra Haemodialysis Centre\nNo. 146 - 148, Tkt Bawah, Jalan Putra 9\nPusat Perniagaan Putra  09000 Kulim  Kedah Darul Aman  MALAYSIA",
    "addressWithUnit": "Darul Aman Ventures, HD Unit",
    "tel": "( 04)4969432",
    "email": "Fax:"
  },
  {
    "name": "Kulim Hospital, HD Unit",
    "sector": "MOH",
    "drInCharge": "LIM YIK SHEN;",
    "address": "",
    "addressWithUnit": "",
    "tel": "",
    "email": ""
  },
  {
    "name": "",
    "sector": "",
    "drInCharge": "",
    "address": "Haemodialysis Unit\nKulim Hospital  09000 Kulim  Kedah Darul Aman  MALAYSIA",
    "addressWithUnit": "Kulim Hospital, HD Unit",
    "tel": "( 04)4272733  3338 /3149",
    "email": "Fax:"
  },
  {
    "name": "Pertubuhan Bakti Fo En Bandar Kulim, HD Unit",
    "sector": "NGO",
    "drInCharge": "LOH LAY KUN;",
    "address": "",
    "addressWithUnit": "",
    "tel": "",
    "email": ""
  },
  {
    "name": "",
    "sector": "",
    "drInCharge": "",
    "address": "Pertubuhan Bakti Fo En Bandar Kulim\nNo. 74, Lorong Semarak 3\nTaman Semarak  09000 Kulim  Kedah Darul Aman  MALAYSIA",
    "addressWithUnit": "Pertubuhan Bakti Fo En Bandar Kulim, HD Unit",
    "tel": "( 04)4918019",
    "email": "Fax:"
  },
  {
    "name": "Pusat Dialisis NKF-Yayasan Sultanah Bahiyah, HD Unit",
    "sector": "NGO",
    "drInCharge": "LAM SWEE WIN;",
    "address": "",
    "addressWithUnit": "",
    "tel": "",
    "email": ""
  },
  {
    "name": "",
    "sector": "",
    "drInCharge": "",
    "address": "Pusat Dialisis NKF-Yayasan Sultanah Bahiyah\nLot 112-113, Taman Kulim Avenue\nKulim Hi Tech Park  09000 Kulim  Kedah Darul Aman  MALAYSIA",
    "addressWithUnit": "Pusat Dialisis NKF-Yayasan Sultanah Bahiyah, HD Unit",
    "tel": "( 04)4080669",
    "email": "Email:"
  },
  {
    "name": "Pusat Hemodialisis Dr Azhar (Kulim Lembah Impiana), HD Unit",
    "sector": "PRIVATE",
    "drInCharge": "TAHIR BIN AHMAD;",
    "address": "",
    "addressWithUnit": "",
    "tel": "",
    "email": ""
  },
  {
    "name": "",
    "sector": "",
    "drInCharge": "",
    "address": "Pusat Hemodialisis Dr Azhar (Kulim Lembah Impiana)\nNo.942 & 943, Jalan Lembah Impiana 6\nTaman Lembah Impiana  09000 Kulim  Kedah Darul Aman  MALAYSIA",
    "addressWithUnit": "Pusat Hemodialisis Dr Azhar (Kulim Lembah Impiana), HD Unit",
    "tel": "04-4904536",
    "email": "eNRR"
  },
  {
    "name": "Pusat Hemodialisis Seroja (Kulim 1), HD Unit",
    "sector": "PRIVATE",
    "drInCharge": "ZARULHISHAM BIN KASSIM;",
    "address": "",
    "addressWithUnit": "",
    "tel": "",
    "email": ""
  },
  {
    "name": "",
    "sector": "",
    "drInCharge": "",
    "address": "Pusat Hemodialisis Seroja Sdn Bhd (Cawangan)\nNo. 6 & 7, Persiaran 1, Kulim Avenue\nKulim Hi-tech Park  09090 Kulim  Kedah Darul Aman  MALAYSIA",
    "addressWithUnit": "Pusat Hemodialisis Seroja (Kulim 1), HD Unit",
    "tel": "( 04)4032449",
    "email": "Fax:"
  },
  {
    "name": "Pusat Hemodialisis Seroja (Kulim 2), HD Unit",
    "sector": "PRIVATE",
    "drInCharge": "ZARULHISHAM BIN KASSIM;",
    "address": "",
    "addressWithUnit": "",
    "tel": "",
    "email": ""
  },
  {
    "name": "",
    "sector": "",
    "drInCharge": "",
    "address": "Pusat Hemodialisis Seroja Sdn Bhd\nNo. 156, Persiaran Avenue 3, Kulim Avenue\nKulim Hi-Tech Park  09000 Kulim  Kedah Darul Aman  MALAYSIA",
    "addressWithUnit": "Pusat Hemodialisis Seroja (Kulim 2), HD Unit",
    "tel": "( 04)4032449",
    "email": "Fax:"
  },
  {
    "name": "Kulim Hospital, Tx Unit",
    "sector": "MOH",
    "drInCharge": "LIM YIK SHEN;",
    "address": "",
    "addressWithUnit": "",
    "tel": "",
    "email": ""
  },
  {
    "name": "",
    "sector": "",
    "drInCharge": "",
    "address": "c/o Hemodialisis Unit\nHospital Kulim\nJalan Mahang  09000 Kulim  Kedah Darul Aman  MALAYSIA",
    "addressWithUnit": "Kulim Hospital, Tx Unit",
    "tel": "044272733  3338 /3149",
    "email": "Fax:"
  },
  {
    "name": "Kulim Hospital, MRRB Unit",
    "sector": "MOH",
    "drInCharge": "LIM YIK SHEN;",
    "address": "",
    "addressWithUnit": "",
    "tel": "",
    "email": ""
  },
  {
    "name": "",
    "sector": "",
    "drInCharge": "",
    "address": "Hospital Kulim\nJln Mahang  09000 Kulim  Kedah Darul Aman  MALAYSIA",
    "addressWithUnit": "Kulim Hospital, MRRB Unit",
    "tel": "( 04)4272733",
    "email": "Doctor in charge"
  },
  {
    "name": "Langkawi",
    "sector": "",
    "drInCharge": "",
    "address": "",
    "addressWithUnit": "",
    "tel": "",
    "email": ""
  },
  {
    "name": "Hospital Sultanah Maliha Langkawi, HD Unit",
    "sector": "MOH",
    "drInCharge": "CHING CHEN HUA;",
    "address": "",
    "addressWithUnit": "",
    "tel": "",
    "email": ""
  },
  {
    "name": "",
    "sector": "",
    "drInCharge": "",
    "address": "Haemodialysis Unit\nHospital Sultanah Maliha Langkawi\nJalan Padang Mat Sirat\nJalan Bukit Tekuh  07000 Langkawi  Kedah Darul Aman  MALAYSIA",
    "addressWithUnit": "Hospital Sultanah Maliha Langkawi, HD Unit",
    "tel": "( 04)9663333  3128",
    "email": "Tel (2):"
  },
  {
    "name": "Lunas",
    "sector": "",
    "drInCharge": "",
    "address": "",
    "addressWithUnit": "",
    "tel": "",
    "email": ""
  },
  {
    "name": "Pusat Rawatan Dialisis Permai Dialysis Sdn Bhd, HD Unit",
    "sector": "PRIVATE",
    "drInCharge": "RADHIYA BINTI MOHD RAZIF;",
    "address": "",
    "addressWithUnit": "",
    "tel": "",
    "email": ""
  },
  {
    "name": "",
    "sector": "",
    "drInCharge": "",
    "address": "Pusat Rawatan Dialisis Permai Dialysis Sdn Bhd\nTingkat Bawah Dan Tingkat Satu\n78, Jalan Saujana 3, Taman Industri Saujana  09600 Lunas  Kedah Darul Aman  MALAYSIA",
    "addressWithUnit": "Pusat Rawatan Dialisis Permai Dialysis Sdn Bhd, HD Unit",
    "tel": "010-3138093",
    "email": "Email:"
  },
  {
    "name": "Padang Serai",
    "sector": "",
    "drInCharge": "",
    "address": "",
    "addressWithUnit": "",
    "tel": "",
    "email": ""
  },
  {
    "name": "Foresight Dialysis Padang Serai, HD Unit",
    "sector": "PRIVATE",
    "drInCharge": "SAFARI BIN KASHMIRAN;",
    "address": "",
    "addressWithUnit": "",
    "tel": "",
    "email": ""
  },
  {
    "name": "",
    "sector": "",
    "drInCharge": "",
    "address": "Foresight Dialysis Padang Serai\nNo. 21 & 22 Lorong 1\nTaman Desa Cinta Sayang\nMukim Pekan Sungai Karangan  09410 Padang Serai  Kedah Darul Aman  MALAYSIA",
    "addressWithUnit": "Foresight Dialysis Padang Serai, HD Unit",
    "tel": "012-6598289",
    "email": "Email:"
  },
  {
    "name": "Pusat Dialisis Serai Wangi, HD Unit",
    "sector": "PRIVATE",
    "drInCharge": "SHAHAROM BINTI ABDULLAH;",
    "address": "",
    "addressWithUnit": "",
    "tel": "",
    "email": ""
  },
  {
    "name": "",
    "sector": "",
    "drInCharge": "",
    "address": "Pusat Dialisis Serai Wangi\n(Kepala Batas Dialysis Centre Sdn Bhd)\nNo. 835,836,837 & 838, Jalan Lagenda 9/2\nTaman Lagenda  09400 Padang Serai  Kedah Darul Aman  MALAYSIA",
    "addressWithUnit": "Pusat Dialisis Serai Wangi, HD Unit",
    "tel": "( 04)4886398",
    "email": "Email:"
  },
  {
    "name": "Pusat Rawatan Dialisis Islah (Kulim), HD Unit",
    "sector": "PRIVATE",
    "drInCharge": "FAKRIYAH BINTI ABDULLAH;",
    "address": "",
    "addressWithUnit": "",
    "tel": "",
    "email": ""
  },
  {
    "name": "",
    "sector": "",
    "drInCharge": "",
    "address": "Pusat Rawatan Dialisis Islah\n(Renal Circle Sdn Bhd)\nNo. 2301 & 2302, Jalan Serai Wangi 10\nPadang Serai  09400 Padang Serai  Kedah Darul Aman  MALAYSIA",
    "addressWithUnit": "Pusat Rawatan Dialisis Islah (Kulim), HD Unit",
    "tel": "(04)4886188",
    "email": "Fax:"
  },
  {
    "name": "Seri Mutiara Dialyisis Centre Sdn Bhd, HD Unit",
    "sector": "PRIVATE",
    "drInCharge": "FAUN CHEE KWAN;",
    "address": "",
    "addressWithUnit": "",
    "tel": "",
    "email": ""
  },
  {
    "name": "",
    "sector": "",
    "drInCharge": "",
    "address": "Seri Mutiara Dialyisis Centre Sdn Bhd\nNo. 3, Lorong Merbau Indah 1,\nTaman Merbau Indah  09410 Padang Serai  Kedah Darul Aman  MALAYSIA",
    "addressWithUnit": "Seri Mutiara Dialyisis Centre Sdn Bhd, HD Unit",
    "tel": "012-5390297",
    "email": "eNRR"
  },
  {
    "name": "Pendang",
    "sector": "",
    "drInCharge": "",
    "address": "",
    "addressWithUnit": "",
    "tel": "",
    "email": ""
  },
  {
    "name": "Pusat Dialisis Davita Pekan Baru, HD Unit",
    "sector": "PRIVATE",
    "drInCharge": "LIM HUI LING;",
    "address": "",
    "addressWithUnit": "",
    "tel": "",
    "email": ""
  },
  {
    "name": "",
    "sector": "",
    "drInCharge": "",
    "address": "Pusat Dialisis Davita Pekan Baru\nNo. 137 (Ground Floor & First Floor) & No. 138 (Ground Floor)\nPekan Pendang Baru  06700 Pendang  Kedah Darul Aman  MALAYSIA",
    "addressWithUnit": "Pusat Dialisis Davita Pekan Baru, HD Unit",
    "tel": "014-9147483",
    "email": "eNRR"
  },
  {
    "name": "Pusat Dialisis Davita Pendang, HD Unit",
    "sector": "PRIVATE",
    "drInCharge": "NG WEI SIONG;",
    "address": "",
    "addressWithUnit": "",
    "tel": "",
    "email": ""
  },
  {
    "name": "",
    "sector": "",
    "drInCharge": "",
    "address": "Pusat Dialisis Davita Pendang\nNo.11, Kawasan Perniagaan Kiara Mas\nJalan Tanah Merah  06700 Pendang  Kedah Darul Aman  MALAYSIA",
    "addressWithUnit": "Pusat Dialisis Davita Pendang, HD Unit",
    "tel": "04-753495",
    "email": "Email:"
  },
  {
    "name": "Pusat Dialisis Nephrocare (Cawangan Pendang), HD Unit",
    "sector": "PRIVATE",
    "drInCharge": "",
    "address": "",
    "addressWithUnit": "",
    "tel": "",
    "email": ""
  },
  {
    "name": "",
    "sector": "",
    "drInCharge": "",
    "address": "Pusat Hemodialisis Syifa (Cawangan Pendang)\nNo. 3, 4, 5, Jalan Saga 1, Taman Saga, \nKilang Kecil Pendang  06720 Pendang  Kedah Darul Aman  MALAYSIA",
    "addressWithUnit": "Pusat Dialisis Nephrocare (Cawangan Pendang), HD Unit",
    "tel": "019-6377382",
    "email": "Fax:"
  },
  {
    "name": "Pusat Rawatan Dialisis Al-Kindi, HD Unit",
    "sector": "PRIVATE",
    "drInCharge": "AZRAF MUHAMMAD FITRI BIN AUZIZ;",
    "address": "",
    "addressWithUnit": "",
    "tel": "",
    "email": ""
  },
  {
    "name": "",
    "sector": "",
    "drInCharge": "",
    "address": "Pusat Rawatan Dialisis Al-Kindi\nNo. 64, Jalan Bandar Baru 3\nPekan Tanah Merah\nTanah Merah  06700 Pendang  Kedah Darul Aman  MALAYSIA",
    "addressWithUnit": "Pusat Rawatan Dialisis Al-Kindi, HD Unit",
    "tel": "04-7590458",
    "email": "Fax:"
  },
  {
    "name": "Unit Hemodialisis Hospital Pendang, HD Unit",
    "sector": "MOH",
    "drInCharge": "FARHANAH BINTI AHMAD KAMAL;",
    "address": "",
    "addressWithUnit": "",
    "tel": "",
    "email": ""
  },
  {
    "name": "",
    "sector": "",
    "drInCharge": "",
    "address": "Unit Hemodialisis Hospital Pendang\nKampung Manggol Pauh  06710 Pendang  Kedah Darul Aman  MALAYSIA",
    "addressWithUnit": "Unit Hemodialisis Hospital Pendang, HD Unit",
    "tel": "04-7251000  1168",
    "email": "Email:"
  },
  {
    "name": "Pokok Sena",
    "sector": "",
    "drInCharge": "",
    "address": "",
    "addressWithUnit": "",
    "tel": "",
    "email": ""
  },
  {
    "name": "Pusat Dialisis Foresight Dialysis Pokok Sena, HD Unit",
    "sector": "PRIVATE",
    "drInCharge": "MOHD HAFIZ NAIM BIN MUSTAFFA;",
    "address": "",
    "addressWithUnit": "",
    "tel": "",
    "email": ""
  },
  {
    "name": "",
    "sector": "",
    "drInCharge": "",
    "address": "Pusat Dialisis Foresight Dialysis Pokok Sena\nNo. A-24, Tingkat Bawah & Tingkat Atas\nTaman Bandar Baru Pokok Sena\nMK Jabi  06400 Pokok Sena  Kedah Darul Aman  MALAYSIA",
    "addressWithUnit": "Pusat Dialisis Foresight Dialysis Pokok Sena, HD Unit",
    "tel": "017-3371912",
    "email": "eNRR"
  },
  {
    "name": "Zaharah Dialisis Centre (Pokok Sena), HD Unit",
    "sector": "PRIVATE",
    "drInCharge": "AHMAD FAKARUDDIN B AHMAD SAMSUDDIN;",
    "address": "",
    "addressWithUnit": "",
    "tel": "",
    "email": ""
  },
  {
    "name": "",
    "sector": "",
    "drInCharge": "",
    "address": "Zaharah Dialysis Centre Sdn Bhd\nNo. 7, Taman Desa Ilmu  06400 Pokok Sena  Kedah Darul Aman  MALAYSIA",
    "addressWithUnit": "Zaharah Dialisis Centre (Pokok Sena), HD Unit",
    "tel": "( 04)7825088",
    "email": "eNRR"
  },
  {
    "name": "Serdang",
    "sector": "",
    "drInCharge": "",
    "address": "",
    "addressWithUnit": "",
    "tel": "",
    "email": ""
  },
  {
    "name": "Pusat Rawatan Dialisis Pusat Dialisis Nur Kasih Sdn Bhd (Cawangan Serdang), HD Unit",
    "sector": "PRIVATE",
    "drInCharge": "NOR SHELINA BINTI RAFI AHMAD;",
    "address": "",
    "addressWithUnit": "",
    "tel": "",
    "email": ""
  },
  {
    "name": "",
    "sector": "",
    "drInCharge": "",
    "address": "Pusat Rawatan Dialisis Pusat Dialisis Nur Kasih Sdn Bhd (Cawangan Serdang)\nPlot 1A (G), 2A (G & 1ST), 3A (G & 1ST)\nJalan Padang, Serdang Avenue  09800 Serdang  Kedah Darul Aman  MALAYSIA",
    "addressWithUnit": "Pusat Rawatan Dialisis Pusat Dialisis Nur Kasih Sdn Bhd (Cawangan Serdang), HD Unit",
    "tel": "04-4078072",
    "email": "eNRR"
  },
  {
    "name": "Sik",
    "sector": "",
    "drInCharge": "",
    "address": "",
    "addressWithUnit": "",
    "tel": "",
    "email": ""
  },
  {
    "name": "Pusat Hemodialisis Mesra, HD Unit",
    "sector": "PRIVATE",
    "drInCharge": "MUHAMAD NAJMI BIN NADZIR;",
    "address": "",
    "addressWithUnit": "",
    "tel": "",
    "email": ""
  },
  {
    "name": "",
    "sector": "",
    "drInCharge": "",
    "address": "Pusat Hemodialisis Mesra\nNo.15, Kompleks Perniagaan Bunga Raya\nSeberang Pekan Sik  08200 Sik  Kedah Darul Aman  MALAYSIA",
    "addressWithUnit": "Pusat Hemodialisis Mesra, HD Unit",
    "tel": "04-4692102",
    "email": "Email:"
  },
  {
    "name": "Sik Hospital, HD Unit",
    "sector": "MOH",
    "drInCharge": "LOW CHUN LEONG;",
    "address": "",
    "addressWithUnit": "",
    "tel": "",
    "email": ""
  },
  {
    "name": "",
    "sector": "",
    "drInCharge": "",
    "address": "Haemodialysis Unit\nSik Hospital  08200 Sik  Kedah Darul Aman  MALAYSIA",
    "addressWithUnit": "Sik Hospital, HD Unit",
    "tel": "( 04)4695333  175",
    "email": "Tel (2):"
  },
  {
    "name": "Sungai Petani",
    "sector": "",
    "drInCharge": "",
    "address": "",
    "addressWithUnit": "",
    "tel": "",
    "email": ""
  },
  {
    "name": "Sultan Abdul Halim Hospital, CAPD Unit",
    "sector": "MOH",
    "drInCharge": "",
    "address": "",
    "addressWithUnit": "",
    "tel": "",
    "email": ""
  },
  {
    "name": "",
    "sector": "",
    "drInCharge": "",
    "address": "CAPD Unit\nHospital Sultan Abdul Halim\nJalan Lencongan Timur\nBandar Aman Jaya  08100 Sungai Petani  Kedah Darul Aman  MALAYSIA",
    "addressWithUnit": "Sultan Abdul Halim Hospital, CAPD Unit",
    "tel": "04-4413807",
    "email": "Email:"
  },
  {
    "name": "Carlatan Dialysis Centre (Sungai Petani), HD Unit",
    "sector": "PRIVATE",
    "drInCharge": "TAN KAH KEONG;",
    "address": "",
    "addressWithUnit": "",
    "tel": "",
    "email": ""
  },
  {
    "name": "",
    "sector": "",
    "drInCharge": "",
    "address": "Carlatan Dialysis Centre (Sungai Petani)\nNo. A24 & A25, Tingkat Bawah Jalan Penaga 1\nTaman Penaga  08000 Sungai Petani  Kedah Darul Aman  MALAYSIA",
    "addressWithUnit": "Carlatan Dialysis Centre (Sungai Petani), HD Unit",
    "tel": "( 04)4312260",
    "email": "Fax:"
  },
  {
    "name": "Dialisis An Nur Taqwa Sdn Bhd, HD Unit",
    "sector": "PRIVATE",
    "drInCharge": "TAN HENG JIN;",
    "address": "",
    "addressWithUnit": "",
    "tel": "",
    "email": ""
  },
  {
    "name": "",
    "sector": "",
    "drInCharge": "",
    "address": "Dialisis An Nur Taqwa Sdn Bhd\nNo. A46 (Ground Gloor & 1st Floor)\nJalan Meranti 2/1\nTaman Desa Meranti, Sg. Pasir  08000 Sungai Petani  Kedah Darul Aman  MALAYSIA",
    "addressWithUnit": "Dialisis An Nur Taqwa Sdn Bhd, HD Unit",
    "tel": "017-2767100",
    "email": "Email:"
  },
  {
    "name": "Dialisis Dr Zur Sdn Bhd, HD Unit",
    "sector": "PRIVATE",
    "drInCharge": "MOHAMAD AKMAL BIN ABDUL KADIR;",
    "address": "",
    "addressWithUnit": "",
    "tel": "",
    "email": ""
  },
  {
    "name": "",
    "sector": "",
    "drInCharge": "",
    "address": "Dialisis Dr Zur Sdn Bhd\nNo. 123A, 124A, 125A & 125B\nJalan PKS (B), Pusat Komersial Saujana  08000 Sungai Petani  Kedah Darul Aman  MALAYSIA",
    "addressWithUnit": "Dialisis Dr Zur Sdn Bhd, HD Unit",
    "tel": "+60174790100",
    "email": "Email:"
  },
  {
    "name": "Metro Specialist Hospital, HD Unit",
    "sector": "PRIVATE",
    "drInCharge": "GAN HWA CHAU;",
    "address": "",
    "addressWithUnit": "",
    "tel": "",
    "email": ""
  },
  {
    "name": "",
    "sector": "",
    "drInCharge": "",
    "address": "Renal Dialysis Unit\nMetro Specialist Hospital\nNo. 1, Lorong Metro  08000 Sungai Petani  Kedah Darul Aman  MALAYSIA",
    "addressWithUnit": "Metro Specialist Hospital, HD Unit",
    "tel": "( 04)4238888  1700",
    "email": "Fax:"
  },
  {
    "name": "Pantai Hospital Laguna Merbok, HD Unit",
    "sector": "PRIVATE",
    "drInCharge": "MUSTAQIM JOY MATHEW BIN ABDULLAH;",
    "address": "",
    "addressWithUnit": "",
    "tel": "",
    "email": ""
  },
  {
    "name": "",
    "sector": "",
    "drInCharge": "",
    "address": "No.1, Lorong BLM 1/10\nBandar Laguna Merbok  08000 Sungai Petani  Kedah Darul Aman  MALAYSIA",
    "addressWithUnit": "Pantai Hospital Laguna Merbok, HD Unit",
    "tel": "04-4260864  191",
    "email": "Tel (2):"
  },
  {
    "name": "Pantai Hospital Sungai Petani, HD Unit",
    "sector": "PRIVATE",
    "drInCharge": "BERNARD CHAN YOON NGEN;",
    "address": "",
    "addressWithUnit": "",
    "tel": "",
    "email": ""
  },
  {
    "name": "",
    "sector": "",
    "drInCharge": "",
    "address": "Pantai Hospital Sungai Petani, HD Unit\nNo. 1, Persiaran Cempaka\nBandar Amanjaya  08000 Sungai Petani  Kedah Darul Aman  MALAYSIA",
    "addressWithUnit": "Pantai Hospital Sungai Petani, HD Unit",
    "tel": "04-4458888  8815",
    "email": "Tel (2):"
  },
  {
    "name": "Pusat Dialisis Davita Sg. Petani Selatan, HD Unit",
    "sector": "PRIVATE",
    "drInCharge": "HUANG YEAN CHYE @ NG YEAN CHYE;",
    "address": "",
    "addressWithUnit": "",
    "tel": "",
    "email": ""
  },
  {
    "name": "",
    "sector": "",
    "drInCharge": "",
    "address": "Quality Dialysis Care Sdn Bhd\nNo. 17, Tkt bawah, Lrg 13\nTaman Petani Jaya  08000 Sungai Petani  Kedah Darul Aman  MALAYSIA",
    "addressWithUnit": "Pusat Dialisis Davita Sg. Petani Selatan, HD Unit",
    "tel": "( 04)4255572",
    "email": "Email:"
  },
  {
    "name": "Pusat Dialisis Davita Sg. Petani Utara, HD Unit",
    "sector": "PRIVATE",
    "drInCharge": "NG HEE THAI;",
    "address": "",
    "addressWithUnit": "",
    "tel": "",
    "email": ""
  },
  {
    "name": "",
    "sector": "",
    "drInCharge": "",
    "address": "Pusat Dialisis Davita Sg. Petani Utara, \n(Quality Dialysis Care Sdn Bhd)\nNo. 270 & 271, Ground Floor, Jalan Lagenda II\nLagenda Height  08000 Sungai Petani  Kedah Darul Aman  MALAYSIA",
    "addressWithUnit": "Pusat Dialisis Davita Sg. Petani Utara, HD Unit",
    "tel": "04-4210503",
    "email": "Fax:"
  },
  {
    "name": "Pusat Dialisis Foresight Dialysis Sungai Petani, HD Unit",
    "sector": "PRIVATE",
    "drInCharge": "NOOR ADZHAR BIN MANSOR;",
    "address": "",
    "addressWithUnit": "",
    "tel": "",
    "email": ""
  },
  {
    "name": "",
    "sector": "",
    "drInCharge": "",
    "address": "Pusat Dialisis Foresight Dialysis Sungai Petani,\nA-220 (Tingkat Bawah) & A-221 (Tingkat Bawah & Aras 1)\nJalan Baiduri 5\nTaman Baiduri  08000 Sungai Petani  Kedah Darul Aman  MALAYSIA",
    "addressWithUnit": "Pusat Dialisis Foresight Dialysis Sungai Petani, HD Unit",
    "tel": "04-4250413",
    "email": "Email:"
  },
  {
    "name": "Pusat Dialisis Ideal, HD Unit",
    "sector": "PRIVATE",
    "drInCharge": "YIP WAI KUEN;",
    "address": "",
    "addressWithUnit": "",
    "tel": "",
    "email": ""
  },
  {
    "name": "",
    "sector": "",
    "drInCharge": "",
    "address": "Pusat Dialisis Ideal Sdn Bhd\nC6, Lebuh Fairuz1\nTaman Perusahaan Rengan Bakar Arang  08000 Sungai Petani  Kedah Darul Aman  MALAYSIA",
    "addressWithUnit": "Pusat Dialisis Ideal, HD Unit",
    "tel": "( 04)4300880",
    "email": "Email:"
  },
  {
    "name": "Pusat Hemodialisis Al Husna, HD Unit",
    "sector": "PRIVATE",
    "drInCharge": "MUHAMAD NAJMI BIN NADZIR;",
    "address": "",
    "addressWithUnit": "",
    "tel": "",
    "email": ""
  },
  {
    "name": "",
    "sector": "",
    "drInCharge": "",
    "address": "Pusat Hemodialisis Al Husna\n4, 5 &6, Lorong 8, Jalan Peruda 1\nTaman Peruda  08000 Sungai Petani  Kedah Darul Aman  MALAYSIA",
    "addressWithUnit": "Pusat Hemodialisis Al Husna, HD Unit",
    "tel": "04-4249090",
    "email": "Email:"
  },
  {
    "name": "Pusat Hemodialisis Beng Siew, HD Unit",
    "sector": "NGO",
    "drInCharge": "TEH SOO KIM;",
    "address": "",
    "addressWithUnit": "",
    "tel": "",
    "email": ""
  },
  {
    "name": "",
    "sector": "",
    "drInCharge": "",
    "address": "Pusat Hemodialisis Beng Siew\nTingkat 3, Plot 137, Jalan Sekerat\nTaman Kampian  08000 Sungai Petani  Kedah Darul Aman  MALAYSIA",
    "addressWithUnit": "Pusat Hemodialisis Beng Siew, HD Unit",
    "tel": "( 04)4211478",
    "email": "Email:"
  },
  {
    "name": "Pusat Rawatan Dialisis Afiat, HD Unit",
    "sector": "PRIVATE",
    "drInCharge": "MUHAMMAD NAHAR BIN MD SHAHID;",
    "address": "",
    "addressWithUnit": "",
    "tel": "",
    "email": ""
  },
  {
    "name": "",
    "sector": "",
    "drInCharge": "",
    "address": "Pusat Rawatan Dialisis Afiat\n(Amal Afiat Sdn Bhd)\nNo. 6, 7 & 8, Jalan Bukit Puteri 9/13\nBandar Puteri Jaya  08000 Sungai Petani  Kedah Darul Aman  MALAYSIA",
    "addressWithUnit": "Pusat Rawatan Dialisis Afiat, HD Unit",
    "tel": "( 04)4215073",
    "email": "Email:"
  },
  {
    "name": "Pusat Rawatan Dialisis Fazwinna, HD Unit",
    "sector": "PRIVATE",
    "drInCharge": "NOOR ADZHAR BIN MANSOR;",
    "address": "",
    "addressWithUnit": "",
    "tel": "",
    "email": ""
  },
  {
    "name": "",
    "sector": "",
    "drInCharge": "",
    "address": "Pusat Rawatan Dialisis Fazwinna\n(Yayasan EMKAY)\nNo. 49 & 50 Lengkok Cempaka 1\nPersiaran Cempaka, Amanjaya  08000 Sungai Petani  Kedah Darul Aman  MALAYSIA",
    "addressWithUnit": "Pusat Rawatan Dialisis Fazwinna, HD Unit",
    "tel": "( 04)4410544",
    "email": "Email:"
  },
  {
    "name": "Sultan Abdul Halim Hospital, HD Unit",
    "sector": "MOH",
    "drInCharge": "LEE KAI QUAN;",
    "address": "",
    "addressWithUnit": "",
    "tel": "",
    "email": ""
  },
  {
    "name": "",
    "sector": "",
    "drInCharge": "",
    "address": "Haemodialysis Unit\nHospital Sultan Abdul Halim\nJalan Lencongan Timur\nBandar Aman Jaya  08000 Sungai Petani  Kedah Darul Aman  MALAYSIA",
    "addressWithUnit": "Sultan Abdul Halim Hospital, HD Unit",
    "tel": "( 04)4219553",
    "email": "Fax:"
  },
  {
    "name": "Sultan Abdul Halim Hospital, Tx Unit",
    "sector": "MOH",
    "drInCharge": "LOW CHUN LEONG;",
    "address": "",
    "addressWithUnit": "",
    "tel": "",
    "email": ""
  },
  {
    "name": "",
    "sector": "",
    "drInCharge": "",
    "address": "Sultan Abdul Halim Hospital\nJalan Lencongan Timur  08000 Sungai Petani  Kedah Darul Aman  MALAYSIA",
    "addressWithUnit": "Sultan Abdul Halim Hospital, Tx Unit",
    "tel": "04-4219553",
    "email": "Email:"
  },
  {
    "name": "Metro Specialist Hospital, MRRB Unit",
    "sector": "PRIVATE",
    "drInCharge": "GAN HWA CHAU;",
    "address": "",
    "addressWithUnit": "",
    "tel": "",
    "email": ""
  },
  {
    "name": "",
    "sector": "",
    "drInCharge": "",
    "address": "Metro Specialist Hospital\n1, Lorong Metro  08000 Sungai Petani  Kedah Darul Aman  MALAYSIA",
    "addressWithUnit": "Metro Specialist Hospital, MRRB Unit",
    "tel": "( 04)4238888",
    "email": "Email:"
  },
  {
    "name": "Sultan Abdul Halim Hospital, MRRB Unit",
    "sector": "MOH",
    "drInCharge": "LOW CHUN LEONG;",
    "address": "",
    "addressWithUnit": "",
    "tel": "",
    "email": ""
  },
  {
    "name": "",
    "sector": "",
    "drInCharge": "",
    "address": "Hospital Sultan Abdul Halim\nJalan Lencongan Timur\nBandar Aman Jaya  08000 Sungai Petani  Kedah Darul Aman  MALAYSIA",
    "addressWithUnit": "Sultan Abdul Halim Hospital, MRRB Unit",
    "tel": "",
    "email": "Panel Nephrologist"
  },
  {
    "name": "Yan",
    "sector": "",
    "drInCharge": "",
    "address": "",
    "addressWithUnit": "",
    "tel": "",
    "email": ""
  },
  {
    "name": "Pusat Hemodialisis Al Falah, HD Unit",
    "sector": "PRIVATE",
    "drInCharge": "MUHAMAD NAJMI BIN NADZIR;",
    "address": "",
    "addressWithUnit": "",
    "tel": "",
    "email": ""
  },
  {
    "name": "",
    "sector": "",
    "drInCharge": "",
    "address": "Pusat Hemodialisis Al Falah\nNo 13 & 13A, Taman Yan\nJalan Dulang  06910 Yan  Kedah Darul Aman  MALAYSIA",
    "addressWithUnit": "Pusat Hemodialisis Al Falah, HD Unit",
    "tel": "04-4655975",
    "email": "Email:"
  },
  {
    "name": "Yan Hospital, HD Unit",
    "sector": "MOH",
    "drInCharge": "CHING CHEN HUA;",
    "address": "",
    "addressWithUnit": "",
    "tel": "",
    "email": ""
  },
  {
    "name": "",
    "sector": "",
    "drInCharge": "",
    "address": "Haemodialysis Unit\nYan Hospital  06900 Yan  Kedah Darul Aman  MALAYSIA",
    "addressWithUnit": "Yan Hospital, HD Unit",
    "tel": "( 04)4655333  1086",
    "email": "Tel (2):"
  }
]